applipy_pg/__init__.py
applipy_pg/py.typed
applipy_pg/version.py
applipy_pg/connections/__init__.py
applipy_pg/connections/connection.py
applipy_pg/connections/handle.py
applipy_pg/connections/module.py
applipy_pg/connections/pool_handle.py
applipy_pg/migrations/__init__.py
applipy_pg/migrations/handle.py
applipy_pg/migrations/migration.py
applipy_pg/migrations/module.py
applipy_pg/migrations/repository.py
applipy_pg-0.3.0.dist-info/LICENSE
applipy_pg-0.3.0.dist-info/METADATA
applipy_pg-0.3.0.dist-info/WHEEL
applipy_pg-0.3.0.dist-info/top_level.txt
applipy_pg-0.3.0.dist-info/RECORD
