Metadata-Version: 2.1
Name: applipy_pg
Version: 0.3.0
Summary: An applipy library for working with PostgreSQL.
Home-page: https://gitlab.com/applipy/applipy_pg
Author: Alessio Linares
Author-email: mail@alessio.cc
License: Apache 2.0
Project-URL: Source, https://gitlab.com/applipy/applipy_pg
Classifier: Development Status :: 5 - Production/Stable
Classifier: Intended Audience :: Developers
Classifier: License :: OSI Approved :: Apache Software License
Classifier: Programming Language :: Python :: 3.12
Classifier: Topic :: Software Development :: Libraries
Requires-Python: >=3.12
License-File: LICENSE
Requires-Dist: applipy<3.0.0,>=2.4.0
Requires-Dist: aiopg<2.0.0,>=1.4.0
Provides-Extra: dev
Requires-Dist: docker==7.1.0; extra == "dev"
Requires-Dist: requests==2.32.3; extra == "dev"
Requires-Dist: pytest==7.4.3; extra == "dev"
Requires-Dist: pytest-asyncio==0.23.2; extra == "dev"
Requires-Dist: pytest-cov==4.1.0; extra == "dev"
Requires-Dist: mypy==1.8.0; extra == "dev"
Requires-Dist: flake8==6.1.0; extra == "dev"
Requires-Dist: testcontainers-postgres==0.0.1rc1; extra == "dev"
